idena/__init__.py
idena/apis/__init__.py
idena/apis/account.py
idena/apis/blockchain.py
idena/apis/contract.py
idena/apis/dna.py
idena/apis/flip.py
idena/apis/net.py
idena/client.py
idena/exceptions.py
idena/method.py
idena/types.py
idena-0.2.2.dist-info/WHEEL
idena-0.2.2.dist-info/METADATA
idena-0.2.2.dist-info/RECORD
