Metadata-Version: 2.1
Name: idena
Version: 0.2.2
Summary: Idena RPC client
Home-page: https://github.com/iRhonin/idena.py
Author: Arash Fatahzade
Author-email: fatahzade@gmail.com
Requires-Python: >=3.6,<4.0
Classifier: Programming Language :: Python :: 3
Classifier: Programming Language :: Python :: 3.6
Classifier: Programming Language :: Python :: 3.7
Classifier: Programming Language :: Python :: 3.8
Classifier: Programming Language :: Python :: 3.9
Requires-Dist: requests (>=2.25.0,<3.0.0)
Project-URL: Repository, https://github.com/iRhonin/idena.py
